smoothmath/__init__.py
smoothmath/evaluate.py
smoothmath/simplemath.py
smoothmath-1.0.4.dist-info/LICENSE
smoothmath-1.0.4.dist-info/METADATA
smoothmath-1.0.4.dist-info/WHEEL
smoothmath-1.0.4.dist-info/top_level.txt
smoothmath-1.0.4.dist-info/RECORD
