Metadata-Version: 2.1
Name: smoothmath
Version: 1.0.4
Summary: A python package that makes math... smooth!
Author-email: qloha <sirfigaloha@gmail.com>
Project-URL: Homepage, https://github.com/qloha/smoothmath
Project-URL: Issues, https://github.com/qloha/smoothmath/issues
Classifier: Programming Language :: Python :: 3
Classifier: License :: OSI Approved :: MIT License
Classifier: Operating System :: OS Independent
Requires-Python: >=3.8
License-File: LICENSE
